mlcroissant/__init__.py
mlcroissant/_src/__init__.py
mlcroissant/_src/beam.py
mlcroissant/_src/datasets.py
mlcroissant/_src/datasets_nonhermetic_test.py
mlcroissant/_src/datasets_test.py
mlcroissant/_src/nodes.py
mlcroissant/_src/core/__init__.py
mlcroissant/_src/core/constants.py
mlcroissant/_src/core/constants_test.py
mlcroissant/_src/core/context.py
mlcroissant/_src/core/context_test.py
mlcroissant/_src/core/data_types.py
mlcroissant/_src/core/dataclasses.py
mlcroissant/_src/core/dataclasses_test.py
mlcroissant/_src/core/dates.py
mlcroissant/_src/core/dates_test.py
mlcroissant/_src/core/git.py
mlcroissant/_src/core/git_test.py
mlcroissant/_src/core/issues.py
mlcroissant/_src/core/issues_test.py
mlcroissant/_src/core/json_ld.py
mlcroissant/_src/core/json_ld_test.py
mlcroissant/_src/core/optional.py
mlcroissant/_src/core/optional_test.py
mlcroissant/_src/core/path.py
mlcroissant/_src/core/rdf.py
mlcroissant/_src/core/rdf_test.py
mlcroissant/_src/core/regex.py
mlcroissant/_src/core/regex_test.py
mlcroissant/_src/core/types.py
mlcroissant/_src/core/url.py
mlcroissant/_src/core/uuid.py
mlcroissant/_src/core/uuid_test.py
mlcroissant/_src/core/versions.py
mlcroissant/_src/core/graphs/__init__.py
mlcroissant/_src/core/graphs/utils.py
mlcroissant/_src/core/ml/__init__.py
mlcroissant/_src/core/ml/bounding_box.py
mlcroissant/_src/core/ml/bounding_box_test.py
mlcroissant/_src/operation_graph/__init__.py
mlcroissant/_src/operation_graph/base_operation.py
mlcroissant/_src/operation_graph/execute.py
mlcroissant/_src/operation_graph/execute_test.py
mlcroissant/_src/operation_graph/graph.py
mlcroissant/_src/operation_graph/operations/__init__.py
mlcroissant/_src/operation_graph/operations/concatenate.py
mlcroissant/_src/operation_graph/operations/concatenate_test.py
mlcroissant/_src/operation_graph/operations/data.py
mlcroissant/_src/operation_graph/operations/data_test.py
mlcroissant/_src/operation_graph/operations/download.py
mlcroissant-1.0.21.dist-info/METADATA
mlcroissant-1.0.21.dist-info/WHEEL
mlcroissant-1.0.21.dist-info/entry_points.txt
mlcroissant-1.0.21.dist-info/top_level.txt
mlcroissant-1.0.21.dist-info/RECORD
