Metadata-Version: 2.4
Name: mlcroissant
Version: 1.0.21
Summary: MLCommons datasets format.
Author: Costanza Conforti, Joaquin Vanschoren, Jos van der Velde, Monjish Bhattacharyya, Omar Benjelloun, Peter Mattson, Pieter Gijsbers, Pierre Marcenac, Pierre Ruyssen, Prabhant Singh
Requires-Dist: absl-py
Requires-Dist: etils[epath]>=1.7.0
Requires-Dist: jsonpath-rw
Requires-Dist: networkx
Requires-Dist: pandas
Requires-Dist: pandas-stubs
Requires-Dist: python-dateutil
Requires-Dist: rdflib
Requires-Dist: requests
Requires-Dist: scipy
Requires-Dist: tqdm
Provides-Extra: dev
Requires-Dist: black==23.11.0; extra == "dev"
Requires-Dist: flake8-docstrings; extra == "dev"
Requires-Dist: mlcroissant[audio]; extra == "dev"
Requires-Dist: mlcroissant[beam]; extra == "dev"
Requires-Dist: mlcroissant[git]; extra == "dev"
Requires-Dist: mlcroissant[image]; extra == "dev"
Requires-Dist: mlcroissant[parquet]; extra == "dev"
Requires-Dist: mypy; extra == "dev"
Requires-Dist: pyflakes; extra == "dev"
Requires-Dist: pygraphviz; extra == "dev"
Requires-Dist: pytest; extra == "dev"
Requires-Dist: pytype; extra == "dev"
Requires-Dist: torchdata; extra == "dev"
Provides-Extra: audio
Requires-Dist: librosa; extra == "audio"
Requires-Dist: soxr==0.4.0b1; extra == "audio"
Provides-Extra: beam
Requires-Dist: apache-beam; extra == "beam"
Provides-Extra: git
Requires-Dist: GitPython; extra == "git"
Provides-Extra: image
Requires-Dist: Pillow; extra == "image"
Provides-Extra: parquet
Requires-Dist: pyarrow; extra == "parquet"
